my_helper.py
helper/__init__.py
helper/examples.txt
helper/main.py
tests/__init__.py
tests/test_main.py
cli_assistant-0.1.1.dist-info/LICENSE.txt
cli_assistant-0.1.1.dist-info/METADATA
cli_assistant-0.1.1.dist-info/WHEEL
cli_assistant-0.1.1.dist-info/entry_points.txt
cli_assistant-0.1.1.dist-info/top_level.txt
cli_assistant-0.1.1.dist-info/RECORD
