Metadata-Version: 2.1
Name: cli-assistant
Version: 0.1.1
Summary: guide you with terminal and git commands
Home-page: https://github.com/willsketch/Helper
Author: william mwine
Author-email: williammwine219@gmail.com
License: MIT License
Classifier: Programming Language :: Python
Classifier: Programming Language :: Python :: 3
Classifier: Programming Language :: Python :: 3.8
License-File: LICENSE.txt
Requires-Dist: openai
